MANIFEST.in
setup.py
ephys_viz_colab/__init__.py
ephys_viz_colab/_version.py
ephys_viz_colab/all_widgets.py
ephys_viz_colab.egg-info/PKG-INFO
ephys_viz_colab.egg-info/SOURCES.txt
ephys_viz_colab.egg-info/dependency_links.txt
ephys_viz_colab.egg-info/requires.txt
ephys_viz_colab.egg-info/top_level.txt
ephys_viz_colab/dist/bundle.js
ephys_viz_colab/widgets/__init__.py
ephys_viz_colab/widgets/AnimalPosition/AnimalPosition.py
ephys_viz_colab/widgets/AnimalPosition/__init__.py
ephys_viz_colab/widgets/AnimalPosition/h5_to_dict.py
ephys_viz_colab/widgets/AnimalPosition2/AnimalPosition2.py
ephys_viz_colab/widgets/AnimalPosition2/__init__.py
ephys_viz_colab/widgets/Autocorrelograms/Autocorrelograms.py
ephys_viz_colab/widgets/Autocorrelograms/__init__.py
ephys_viz_colab/widgets/ElectrodeGeometry/ElectrodeGeometry.py
ephys_viz_colab/widgets/ElectrodeGeometry/__init__.py
ephys_viz_colab/widgets/NWBBrowser/NWBBrowser.py
ephys_viz_colab/widgets/NWBBrowser/__init__.py
ephys_viz_colab/widgets/NWBBrowser/h5_to_dict.py
ephys_viz_colab/widgets/NWBView/NWBView.py
ephys_viz_colab/widgets/NWBView/__init__.py
ephys_viz_colab/widgets/NWBView/h5_to_dict.py
ephys_viz_colab/widgets/PlaceField/PlaceField.py
ephys_viz_colab/widgets/PlaceField/__init__.py
ephys_viz_colab/widgets/SpikeForestAnalysis/SpikeForestAnalysis.py
ephys_viz_colab/widgets/SpikeForestAnalysis/__init__.py
ephys_viz_colab/widgets/TimeseriesView/TimeseriesView.py
ephys_viz_colab/widgets/TimeseriesView/__init__.py
ephys_viz_colab/widgets/pycommon/__init__.py
ephys_viz_colab/widgets/pycommon/nwb_to_dict.py