Metadata-Version: 1.1
Name: ephys-viz-colab
Version: 0.1.1
Summary: Neurophysiology visualization widgets
Home-page: UNKNOWN
Author: Jeremy Magland
Author-email: UNKNOWN
License: UNKNOWN
Platform: UNKNOWN
Classifier: Programming Language :: Python :: 3
Classifier: License :: OSI Approved :: Apache Software License
Classifier: Operating System :: OS Independent
